{
  "basics": {
    "name": "John Doe",
    "label": "developer",
    "image": "https://user-images.githubusercontent.com/10413754/79948155-e5e9da80-84a5-11ea-83eb-34e2f5aa89f6.png",
    "email": "johndoe@gmail.com",
    "phone": "(111) 333-4567",
    "url": "http://johndoe.com",
    "summary": "Lorem ipsum dolor sit amet, consectetur adipiscing elit, sed do eiusmod tempor incididunt ut labore et dolore magna aliqua. Ut enim ad minim veniam, quis nostrud exercitation ullamco laboris nisi ut aliquip ex ea commodo consequat.",
    "location": {
      "address": "22111 Makiling",
      "postalCode": "4027",
      "city": "Calamba",
      "countryCode": "PH",
      "region": "Philippines"
    },
    "profiles": [{
      "network": "Twitter",
      "username": "johndoe",
      "url": "http://twitter.com/johndoe"
    }]
  },
  "work": [{
    "name": "Company",
    "position": "Developer",
    "url": "http://somecompany.com",
    "startDate": "2020-01-01",
    "endDate": "2020-01-01",
    "summary": "Lorem ipsum dolor sit amet, consectetur adipiscing elit, sed do eiusmod tempor incididunt ut labore et dolore magna aliqua. Ut enim ad minim veniam, quis nostrud exercitation ullamco laboris nisi ut aliquip ex ea commodo consequat.",
    "highlights": [
      "Lead Developer of Innovation hub"
    ]
  }],
  "volunteer": [{
    "organization": "Organization",
    "position": "Volunteer",
    "url": "http://organization.com/",
    "startDate": "2020-01-01",
    "endDate": "2020-01-01",
    "summary": "Lorem ipsum dolor sit amet, consectetur adipiscing elit, sed do eiusmod tempor incididunt ut labore et dolore magna aliqua. Ut enim ad minim veniam, quis nostrud exercitation ullamco laboris nisi ut aliquip ex ea commodo consequat.",
    "highlights": [
      "Awarded 'Volunteer of the Month'"
    ]
  }],
  "education": [{
    "institution": "University",
    "url": "https://institution.ph",
    "area": "Software Development",
    "studyType": "Bachelor",
    "startDate": "2020-01-01",
    "endDate": "2020-01-01",
    "score": "4.0",
    "courses": [
      "WEB101 - Web Development",
      "SYS123 - Object Oriented Programming"
    ]
  }],
  "awards": [{
    "title": "Award",
    "date": "2020-11-01",
    "awarder": "Company",
    "summary": "Programmer of the Year 2020"
  }],
  "publications": [{
    "name": "Publication",
    "publisher": "Company",
    "releaseDate": "2020-10-01",
    "url": "http://publication.com",
    "summary": "Lorem ipsum dolor sit amet, consectetur adipiscing elit, sed do eiusmod tempor incididunt ut labore et dolore magna aliqua. Ut enim ad minim veniam, quis nostrud exercitation ullamco laboris nisi ut aliquip ex ea commodo consequat."
  }],
  "skills": [{
    "name": "Web Development",
    "level": "Master",
    "keywords": [
      "HTML",
      "CSS",
      "Javascript"
    ]
  }],
  "languages": [{
    "language": "English",
    "fluency": "Native speaker"
  }],
  "interests": [{
    "name": "Electronics",
    "keywords": [
      "PCB",
      "IOT"
    ],
    "description": "Lorem ipsum dolor sit amet, consectetur adipiscing elit, sed do eiusmod tempor incididunt ut labore et dolore magna aliqua. Ut enim ad minim veniam, quis nostrud exercitation ullamco laboris nisi ut aliquip ex ea commodo consequat."
  }],
  "references": [{
    "name": "Jane Doe",
    "reference": "Lorem ipsum dolor sit amet, consectetur adipiscing elit, sed do eiusmod tempor incididunt ut labore et dolore magna aliqua. Ut enim ad minim veniam, quis nostrud exercitation ullamco laboris nisi ut aliquip ex ea commodo consequat."
  }],
  "projects": [
    {
      "name": "Project Name",
      "description": "Description...",
      "highlights": [ 
        "COVID19 Patient Tracker"
      ],
      "keywords": [
        "PHP", "NodeJS", "Javascript"
      ],
      "startDate": "2020-01-01",
      "endDate": "2020-01-01",
      "url": "https://project.example.com",
      "roles": [ 
        "Lead Developer", "Designer"
      ],
      "image": "https://user-images.githubusercontent.com/10413754/79948155-e5e9da80-84a5-11ea-83eb-34e2f5aa89f6.png",
      "entity": "Facebook, Google, Microsoft, Amazon",
      "type": "web application"
    }
  ]
}
